extra_whisper/__init__.py
extra_whisper/downloader.py
extra_whisper/transcribe.py
extra_whisper-0.4.0.dist-info/LICENSE
extra_whisper-0.4.0.dist-info/METADATA
extra_whisper-0.4.0.dist-info/WHEEL
extra_whisper-0.4.0.dist-info/RECORD
