Metadata-Version: 2.1
Name: extra-whisper
Version: 0.4.0
Summary: Extended faster-whisper with yt-dlp remote media transcription
Author: mohammadmansour200
Author-email: mohammadamansour03@gmail.com
Requires-Python: >=3.10
Classifier: Programming Language :: Python :: 3
Classifier: Programming Language :: Python :: 3.10
Classifier: Programming Language :: Python :: 3.11
Classifier: Programming Language :: Python :: 3.12
Requires-Dist: faster-whisper (>=1.2.1)
Requires-Dist: validators (>=0.35.0,<0.36.0)
Requires-Dist: yt-dlp (>=2025.10.22)
